{
	"id": "QJcmKcEKSZyreS8",
	"json": "{\"id\":\"QJcmKcEKSZyreS8\",\"url\":\"https://appsumo.com/products/tidycal/\",\"loadedUrl\":\"https://appsumo.com/products/tidycal/\",\"uniqueKey\":\"https://appsumo.com/products/tidycal\",\"method\":\"GET\",\"noRetry\":false,\"retryCount\":0,\"errorMessages\":[],\"headers\":{},\"userData\":{\"__crawlee\":{\"crawlDepth\":1,\"enqueueStrategy\":\"same-domain\",\"state\":4}},\"handledAt\":\"2026-07-02T04:34:46.977Z\"}",
	"method": "GET",
	"orderNo": null,
	"retryCount": 0,
	"uniqueKey": "https://appsumo.com/products/tidycal",
	"url": "https://appsumo.com/products/tidycal/"
}